gff3toddbj/__init__.py
gff3toddbj/ddbj_filter.toml
gff3toddbj/evaluate.py
gff3toddbj/formatter.py
gff3toddbj/genbank_to_ddbj.py
gff3toddbj/io.py
gff3toddbj/main.py
gff3toddbj/metadata.toml
gff3toddbj/metadata_without_COMMON.toml
gff3toddbj/parser.py
gff3toddbj/transforms.py
gff3toddbj/translate_features_qualifiers.toml
gff3toddbj/utils.py
gff3toddbj/version.py
gff3toddbj-0.4.3.dist-info/licenses/LICENSE
tools/__init__.py
tools/list_products/__init__.py
tools/list_products/list_products.py
tools/normalize_seqids/__init__.py
tools/normalize_seqids/normalize_seqids.py
tools/splitfasta/__init__.py
tools/splitfasta/split_fasta.py
gff3toddbj-0.4.3.dist-info/METADATA
gff3toddbj-0.4.3.dist-info/WHEEL
gff3toddbj-0.4.3.dist-info/entry_points.txt
gff3toddbj-0.4.3.dist-info/top_level.txt
gff3toddbj-0.4.3.dist-info/RECORD
