Metadata-Version: 2.4
Name: gff3toddbj
Version: 0.4.3
Summary: Create a DDBJ annotation file from GFF3 and FASTA files
Author-email: Yamato Matsuoka <yamaton@gmail.com>
Project-URL: Homepage, https://github.com/yamaton/gff3toddbj
Project-URL: Bug Tracker, https://github.com/yamaton/gff3toddbj/issues
Classifier: Programming Language :: Python :: 3
Classifier: License :: OSI Approved :: GNU General Public License v3 (GPLv3)
Classifier: Operating System :: OS Independent
Classifier: Development Status :: 3 - Alpha
Requires-Python: <3.14,>=3.9
License-File: LICENSE
Requires-Dist: biopython<=1.86
Requires-Dist: bcbio-gff<=0.7.1
Requires-Dist: pysam
Requires-Dist: toml
Dynamic: license-file
